{
  "timestamp" : "2023-08-12T00:41:21Z",
  "count_outdated" : 936,
  "uniques_outdated" : 414,
  "count" : 949,
  "uniques" : 423,
  "clones" : [
    {
      "timestamp": "2023-07-29T00:00:00Z",
      "count": 2,
      "count_minmax": [ 1, 2 ],
      "count_decinc": [ 0, 2 ],
      "uniques": 1,
      "uniques_minmax": [ 1, 1 ],
      "uniques_decinc": [ 0, 1 ]
    },
    {
      "timestamp": "2023-07-30T00:00:00Z",
      "count": 2,
      "count_minmax": [ 1, 2 ],
      "count_decinc": [ 0, 2 ],
      "uniques": 1,
      "uniques_minmax": [ 1, 1 ],
      "uniques_decinc": [ 0, 1 ]
    },
    {
      "timestamp": "2023-08-03T00:00:00Z",
      "count": 1,
      "count_minmax": [ 1, 1 ],
      "count_decinc": [ 0, 1 ],
      "uniques": 1,
      "uniques_minmax": [ 1, 1 ],
      "uniques_decinc": [ 0, 1 ]
    },
    {
      "timestamp": "2023-08-05T00:00:00Z",
      "count": 2,
      "count_minmax": [ 2, 2 ],
      "count_decinc": [ 0, 2 ],
      "uniques": 1,
      "uniques_minmax": [ 1, 1 ],
      "uniques_decinc": [ 0, 1 ]
    },
    {
      "timestamp": "2023-08-09T00:00:00Z",
      "count": 1,
      "count_minmax": [ 1, 1 ],
      "count_decinc": [ 0, 1 ],
      "uniques": 1,
      "uniques_minmax": [ 1, 1 ],
      "uniques_decinc": [ 0, 1 ]
    },
    {
      "timestamp": "2023-08-10T00:00:00Z",
      "count": 2,
      "count_minmax": [ 1, 2 ],
      "count_decinc": [ 0, 2 ],
      "uniques": 1,
      "uniques_minmax": [ 1, 1 ],
      "uniques_decinc": [ 0, 1 ]
    },
    {
      "timestamp": "2023-08-11T00:00:00Z",
      "count": 3,
      "count_minmax": [ 1, 3 ],
      "count_decinc": [ 0, 3 ],
      "uniques": 3,
      "uniques_minmax": [ 1, 3 ],
      "uniques_decinc": [ 0, 3 ]
    }
  ]
}
